odoo/addons/stock_shifting_end_of_lot/README.rst
odoo/addons/stock_shifting_end_of_lot/__init__.py
odoo/addons/stock_shifting_end_of_lot/__manifest__.py
odoo/addons/stock_shifting_end_of_lot/data/organisation_demo.xml
odoo/addons/stock_shifting_end_of_lot/data/product_demo.xml
odoo/addons/stock_shifting_end_of_lot/data/stock_demo.xml
odoo/addons/stock_shifting_end_of_lot/i18n/fr.po
odoo/addons/stock_shifting_end_of_lot/i18n/stock_shifting_end_of_lot.pot
odoo/addons/stock_shifting_end_of_lot/models/__init__.py
odoo/addons/stock_shifting_end_of_lot/models/stock_picking.py
odoo/addons/stock_shifting_end_of_lot/models/stock_picking_type.py
odoo/addons/stock_shifting_end_of_lot/readme/CONFIGURE.rst
odoo/addons/stock_shifting_end_of_lot/readme/CONTRIBUTORS.rst
odoo/addons/stock_shifting_end_of_lot/readme/DESCRIPTION.rst
odoo/addons/stock_shifting_end_of_lot/static/description/conf.png
odoo/addons/stock_shifting_end_of_lot/static/description/icon.png
odoo/addons/stock_shifting_end_of_lot/static/description/index.html
odoo/addons/stock_shifting_end_of_lot/static/description/main.png
odoo/addons/stock_shifting_end_of_lot/static/description/transfer.png
odoo/addons/stock_shifting_end_of_lot/tests/__init__.py
odoo/addons/stock_shifting_end_of_lot/tests/test_shifting.py
odoo/addons/stock_shifting_end_of_lot/views/picking_type.xml
odoo12_addon_stock_shifting_end_of_lot-12.0.1.0.2.dist-info/METADATA
odoo12_addon_stock_shifting_end_of_lot-12.0.1.0.2.dist-info/WHEEL
odoo12_addon_stock_shifting_end_of_lot-12.0.1.0.2.dist-info/top_level.txt
odoo12_addon_stock_shifting_end_of_lot-12.0.1.0.2.dist-info/RECORD
